examples/README.md
examples/__init__.py
examples/applications/__init__.py
examples/applications/affective_signaling_multirobot.py
examples/applications/gaze_mirroring_multisensor.py
examples/applications/wrapyfi_configs/affective_signaling_multirobot/COMP_mainpc.yml
examples/applications/wrapyfi_configs/affective_signaling_multirobot/OPT_icubpc.yml
examples/applications/wrapyfi_configs/affective_signaling_multirobot/OPT_pepperpc.yml
examples/applications/wrapyfi_configs/gaze_mirroring_multisensor/COMP_mainpc.yml
examples/applications/wrapyfi_configs/gaze_mirroring_multisensor/OPT_camera.yml
examples/communication_patterns/__init__.py
examples/communication_patterns/request_reply_example.py
examples/communication_patterns/transceive_reemit_example.py
examples/communication_schemes/__init__.py
examples/communication_schemes/channeling_example.py
examples/communication_schemes/forwarding_example.py
examples/communication_schemes/mirroring_example.py
examples/custom_msgs/__init__.py
examples/custom_msgs/ros2_message_example.py
examples/custom_msgs/ros_message_example.py
examples/custom_msgs/ros_parameter_example.py
examples/encoders/__init__.py
examples/encoders/astropy_example.py
examples/encoders/cupy_example.py
examples/encoders/dask_example.py
examples/encoders/jax_example.py
examples/encoders/mxnet_example.py
examples/encoders/numpy_pandas_example.py
examples/encoders/paddlepaddle_example.py
examples/encoders/pillow_example.py
examples/encoders/pint_example.py
examples/encoders/plugins/__init__.py
examples/encoders/plugins/astropy_tables.py
examples/encoders/pyarrow_example.py
examples/encoders/pytorch_example.py
examples/encoders/tensorflow_example.py
examples/encoders/trax_example.py
examples/encoders/xarray_example.py
examples/encoders/zarr_example.py
examples/hello_world.py
examples/requirements.txt
examples/robots/__init__.py
examples/robots/icub_head.py
examples/sensors/__init__.py
examples/sensors/cam_mic.py
examples/websockets/__init__.py
wrapyfi-0.5.0.dist-info/METADATA
wrapyfi-0.5.0.dist-info/WHEEL
wrapyfi-0.5.0.dist-info/entry_points.txt
wrapyfi-0.5.0.dist-info/licenses/LICENSE
wrapyfi-0.5.0.dist-info/RECORD
