Metadata-Version: 2.1
Name: wrapyfi
Version: 0.5.0
Summary: Wrapyfi is a wrapper for simplifying Middleware communication
Author-Email: Fares Abawi <f.abawi@outlook.com>
Maintainer-Email: Fares Abawi <f.abawi@outlook.com>
Classifier: Development Status :: 4 - Beta
Classifier: Intended Audience :: Developers
Classifier: Intended Audience :: Information Technology
Classifier: Intended Audience :: Science/Research
Classifier: License :: OSI Approved :: MIT License
Classifier: Operating System :: POSIX :: Linux
Classifier: Programming Language :: Python :: 3.10
Classifier: Programming Language :: Python :: 3.11
Classifier: Programming Language :: Python :: 3.6
Classifier: Programming Language :: Python :: 3.7
Classifier: Programming Language :: Python :: 3.8
Classifier: Programming Language :: Python :: 3.9
Classifier: Topic :: Scientific/Engineering :: Artificial Intelligence
Classifier: Topic :: Scientific/Engineering :: Human Machine Interfaces
Classifier: Topic :: System :: Distributed Computing
Classifier: Operating System :: Microsoft :: Windows :: Windows 10
Classifier: Operating System :: Microsoft :: Windows :: Windows 11
Project-URL: Homepage, https://github.com/fabawi/wrapyfi/blob/main/
Project-URL: Documentation, https://wrapyfi.readthedocs.io/en/latest/
Project-URL: Source, https://github.com/fabawi/wrapyfi/
Project-URL: Tracker, https://github.com/fabawi/wrapyfi/issues
Requires-Python: >=3.6
Requires-Dist: pyyaml>=5.1.1
Requires-Dist: setuptools>=59.6.0
Provides-Extra: docs
Requires-Dist: myst_parser; extra == "docs"
Requires-Dist: sphinx; extra == "docs"
Requires-Dist: sphinx_rtd_theme; extra == "docs"
Provides-Extra: pyzmq
Requires-Dist: pyzmq>=19.0.0; extra == "pyzmq"
Provides-Extra: numpy
Requires-Dist: numpy>=1.19.2; extra == "numpy"
Provides-Extra: websocket
Requires-Dist: python-socketio>=5.0.4; extra == "websocket"
Requires-Dist: python_socketio>=5.0.4; extra == "websocket"
Provides-Extra: zenoh
Requires-Dist: eclipse-zenoh>=1.0.0; extra == "zenoh"
Provides-Extra: mqtt
Requires-Dist: paho-mqtt>=2.0; extra == "mqtt"
Provides-Extra: headless
Requires-Dist: wrapyfi[numpy]; extra == "headless"
Requires-Dist: wrapyfi[pyzmq]; extra == "headless"
Requires-Dist: opencv-python-headless>=4.2.0; extra == "headless"
Provides-Extra: headless-websocket
Requires-Dist: wrapyfi[numpy]; extra == "headless-websocket"
Requires-Dist: wrapyfi[websocket]; extra == "headless-websocket"
Requires-Dist: opencv-python-headless>=4.2.0; extra == "headless-websocket"
Provides-Extra: headless-zenoh
Requires-Dist: wrapyfi[numpy]; extra == "headless-zenoh"
Requires-Dist: wrapyfi[zenoh]; extra == "headless-zenoh"
Requires-Dist: opencv-python-headless>=4.2.0; extra == "headless-zenoh"
Provides-Extra: headless-mqtt
Requires-Dist: wrapyfi[numpy]; extra == "headless-mqtt"
Requires-Dist: wrapyfi[mqtt]; extra == "headless-mqtt"
Requires-Dist: opencv-python-headless>=4.2.0; extra == "headless-mqtt"
Provides-Extra: complete
Requires-Dist: wrapyfi[numpy]; extra == "complete"
Requires-Dist: sounddevice; extra == "complete"
Requires-Dist: soundfile; extra == "complete"
Requires-Dist: Pillow; extra == "complete"
Requires-Dist: pandas; extra == "complete"
Requires-Dist: wrapyfi[pyzmq]; extra == "complete"
Requires-Dist: wrapyfi[websocket]; extra == "complete"
Requires-Dist: wrapyfi[zenoh]; extra == "complete"
Requires-Dist: wrapyfi[mqtt]; extra == "complete"
Requires-Dist: wrapyfi[docs]; extra == "complete"
Requires-Dist: opencv-contrib-python>=4.2.0; extra == "complete"
Provides-Extra: all
Requires-Dist: wrapyfi[numpy]; extra == "all"
Requires-Dist: wrapyfi[pyzmq]; extra == "all"
Requires-Dist: opencv-contrib-python>=4.2.0; extra == "all"
